ld_patch/__init__.py
ld_patch/ld_patch.py
ld_feature_patch-1.0.0.dist-info/AUTHORS.rst
ld_feature_patch-1.0.0.dist-info/LICENSE
ld_feature_patch-1.0.0.dist-info/METADATA
ld_feature_patch-1.0.0.dist-info/WHEEL
ld_feature_patch-1.0.0.dist-info/top_level.txt
ld_feature_patch-1.0.0.dist-info/RECORD
