Metadata-Version: 2.1
Name: ld-feature-patch
Version: 1.0.0
Summary: Patch Launch Darkly feature flags for unit testing
Home-page: https://github.com/pymetrics/ld-feature-patch
Author: Chris Lawlor
Author-email: chris@pymetrics.com
License: Apache Software License 2.0
Keywords: Launch Darkly,testing,pytest,unit test
Classifier: Development Status :: 2 - Pre-Alpha
Classifier: Intended Audience :: Developers
Classifier: License :: OSI Approved :: Apache Software License
Classifier: Natural Language :: English
Classifier: Programming Language :: Python :: 3
Classifier: Programming Language :: Python :: 3.7
Classifier: Programming Language :: Python :: 3.8
Classifier: Programming Language :: Python :: 3.9
Classifier: Programming Language :: Python :: 3.10
Classifier: Programming Language :: Python :: 3.11
Classifier: Programming Language :: Python :: 3.12
Classifier: Framework :: Pytest
Classifier: Topic :: Software Development :: Testing
Requires-Python: >=3.5
License-File: LICENSE
License-File: AUTHORS.rst
Requires-Dist: launchdarkly-server-sdk
